alu_4bit.v
`timescale 1ns / 1ps
//////////////////////////////////////////////////////////////////////////////////
// Company: 
// Engineer: 
// 
// Create Date: 16.05.2025 14:29:57
// Design Name: 
// Module Name: alu_4bit
// Project Name: 
// Target Devices: 
// Tool Versions: 
// Description: 
// 
// Dependencies: 
// 
// Revision:
// Revision 0.01 - File Created
// Additional Comments:
// 
//////////////////////////////////////////////////////////////////////////////////


module alu_4bit(
    input  [3:0] A,        // 4-bit input A
    input  [3:0] B,        // 4-bit input B
    input  [2:0] op,       // 3-bit operation code
    output reg [3:0] result, // 4-bit result
    output reg cout,       // Carry out
    output reg zero        // Zero flag
);

    always @(*) begin
        // Default values
        result = 4'b0000;
        cout   = 1'b0;
        zero   = 1'b0;

        case (op)
            3'b000: begin // Addition
                {cout, result} = A + B;
            end
            3'b001: begin // Subtraction
                {cout, result} = A - B;
            end
            3'b010: begin // AND
                result = A & B;
                cout   = 1'b0;
            end
            3'b011: begin // OR
                result = A | B;
                cout   = 1'b0;
            end
            3'b100: begin // XOR
                result = A ^ B;
                cout   = 1'b0;
            end
            default: begin // Reserved
                result = 4'b0000;
                cout   = 1'b0;
            end
        endcase

        // Zero flag: set if result is 0
        zero = (result == 4'b0000);
    end

endmodule

alu_4bit_tb.v
`timescale 1ns / 1ps
//////////////////////////////////////////////////////////////////////////////////
// Company: 
// Engineer: 
// 
// Create Date: 16.05.2025 14:32:00
// Design Name: 
// Module Name: alu_4bit_tb
// Project Name: 
// Target Devices: 
// Tool Versions: 
// Description: 
// 
// Dependencies: 
// 
// Revision:
// Revision 0.01 - File Created
// Additional Comments:
// 
//////////////////////////////////////////////////////////////////////////////////


module alu_4bit_tb;

    // Testbench signals
    reg  [3:0] A, B;
    reg  [2:0] op;
    wire [3:0] result;
    wire cout, zero;

    // Instantiate the ALU
    alu_4bit uut (
        .A(A),
        .B(B),
        .op(op),
        .result(result),
        .cout(cout),
        .zero(zero)
    );

    // Test procedure
    initial begin
        // Initialize inputs
        A  = 4'b0000;
        B  = 4'b0000;
        op = 3'b000;

        // Open VCD file for waveform
        $dumpfile("alu_4bit_tb.vcd");
        $dumpvars(0, alu_4bit_tb);

        // Test each operation
        $display("Testing 4-bit ALU...");

        // Test Addition (op = 000)
        #10;
        op = 3'b000; A = 4'b0011; B = 4'b0101; // 3 + 5 = 8
        #10;
        $display("Add: A=%b, B=%b, result=%b, cout=%b, zero=%b", A, B, result, cout, zero);
        A = 4'b1111; B = 4'b0001; // 15 + 1 = 16 (overflow)
        #10;
        $display("Add: A=%b, B=%b, result=%b, cout=%b, zero=%b", A, B, result, cout, zero);

        // Test Subtraction (op = 001)
        #10;
        op = 3'b001; A = 4'b0101; B = 4'b0011; // 5 - 3 = 2
        #10;
        $display("Sub: A=%b, B=%b, result=%b, cout=%b, zero=%b", A, B, result, cout, zero);
        A = 4'b0000; B = 4'b0000; // 0 - 0 = 0
        #10;
        $display("Sub: A=%b, B=%b, result=%b, cout=%b, zero=%b", A, B, result, cout, zero);

        // Test AND (op = 010)
        #10;
        op = 3'b010; A = 4'b1100; B = 4'b1010; // 1100 & 1010 = 1000
        #10;
        $display("AND: A=%b, B=%b, result=%b, cout=%b, zero=%b", A, B, result, cout, zero);
        A = 4'b0000; B = 4'b1111; // 0000 & 1111 = 0000
        #10;
        $display("AND: A=%b, B=%b, result=%b, cout=%b, zero=%b", A, B, result, cout, zero);

        // Test OR (op = 011)
        #10;
        op = 3'b011; A = 4'b1100; B = 4'b1010; // 1100 | 1010 = 1110
        #10;
        $display("OR:  A=%b, B=%b, result=%b, cout=%b, zero=%b", A, B, result, cout, zero);
        A = 4'b0000; B = 4'b0000; // 0000 | 0000 = 0000
        #10;
        $display("OR:  A=%b, B=%b, result=%b, cout=%b, zero=%b", A, B, result, cout, zero);

        // Test XOR (op = 100)
        #10;
        op = 3'b100; A = 4'b1100; B = 4'b1010; // 1100 ^ 1010 = 0110
        #10;
        $display("XOR: A=%b, B=%b, result=%b, cout=%b, zero=%b", A, B, result, cout, zero);
        A = 4'b1111; B = 4'b1111; // 1111 ^ 1111 = 0000
        #10;
        $display("XOR: A=%b, B=%b, result=%b, cout=%b, zero=%b", A, B, result, cout, zero);

        // Test invalid op (e.g., 101)
        #10;
        op = 3'b101; A = 4'b1010; B = 4'b0101;
        #10;
        $display("Invalid op: A=%b, B=%b, result=%b, cout=%b, zero=%b", A, B, result, cout, zero);

        // End simulation
        #10;
        $display("Test completed.");
        $finish;
    end

endmodule

alu_4bit_tb.vcd
$date
   Fri May 16 14:39:41 2025
$end

$version
  2023.2
  $dumpfile ("alu_4bit_tb.vcd") 
$end

$timescale
  1ps
$end

$scope module alu_4bit_tb $end
$var reg 4 ! A [3:0] $end
$var reg 4 " B [3:0] $end
$var reg 3 # op [2:0] $end
$var wire 4 $ result [3:0] $end
$var wire 1 % cout $end
$var wire 1 & zero $end
$scope module uut $end
$var wire 4 ' A [3:0] $end
$var wire 4 ( B [3:0] $end
$var wire 3 ) op [2:0] $end
$var reg 4 * result [3:0] $end
$var reg 1 + cout $end
$var reg 1 , zero $end
$upscope $end
$upscope $end
$enddefinitions $end

#0
$dumpvars
b0 !
b0 "
b0 #
b0 $
0%
1&
b0 '
b0 (
b0 )
b0 *
0+
1,
$end

#10000
b11 !
b101 "
b1000 $
0&
b11 '
b101 (
b1000 *
0,

#20000
b1111 !
b1 "
b0 $
1%
1&
b1111 '
b1 (
b0 *
1+
1,

#40000
b101 !
b11 "
b1 #
b10 $
0%
0&
b101 '
b11 (
b1 )
b10 *
0+
0,

#50000
b0 !
b0 "
b0 $
1&
b0 '
b0 (
b0 *
1,

#70000
b1100 !
b1010 "
b10 #
b1000 $
0&
b1100 '
b1010 (
b10 )
b1000 *
0,

#80000
b0 !
b1111 "
b0 $
1&
b0 '
b1111 (
b0 *
1,

#100000
b1100 !
b1010 "
b11 #
b1110 $
0&
b1100 '
b1010 (
b11 )
b1110 *
0,

#110000
b0 !
b0 "
b0 $
1&
b0 '
b0 (
b0 *
1,

#130000
b1100 !
b1010 "
b100 #
b110 $
0&
b1100 '
b1010 (
b100 )
b110 *
0,

#140000
b1111 !
b1111 "
b0 $
1&
b1111 '
b1111 (
b0 *
1,
